Metadata-Version: 2.1
Name: xlagent
Version: 0.2.2
Summary: A lightweight framework for building LLM-based agents
Home-page: https://github.com/InternLM/lagent
License: Apache 2.0
Keywords: artificial general intelligence,agent,agi,llm
License-File: LICENSE
Requires-Dist: arxiv
Requires-Dist: distro
Requires-Dist: filelock
Requires-Dist: func-timeout
Requires-Dist: griffe
Requires-Dist: json5
Requires-Dist: jsonschema
Requires-Dist: jupyter
Requires-Dist: jupyter-client
Requires-Dist: phx-class-registry
Requires-Dist: requests
Requires-Dist: streamlit
Requires-Dist: tiktoken
Requires-Dist: timeout-decorator
Requires-Dist: typing-extensions
Requires-Dist: duckduckgo-search ==5.3.1b1
Provides-Extra: all
Requires-Dist: google-search-results ; extra == 'all'
Requires-Dist: lmdeploy >=0.2.3 ; extra == 'all'
Requires-Dist: pillow ; extra == 'all'
Requires-Dist: python-pptx ; extra == 'all'
Requires-Dist: timeout-decorator ; extra == 'all'
Requires-Dist: torch ; extra == 'all'
Requires-Dist: transformers >=4.34 ; extra == 'all'
Requires-Dist: vllm >=0.3.3 ; extra == 'all'
Requires-Dist: arxiv ; extra == 'all'
Requires-Dist: distro ; extra == 'all'
Requires-Dist: filelock ; extra == 'all'
Requires-Dist: func-timeout ; extra == 'all'
Requires-Dist: griffe ; extra == 'all'
Requires-Dist: json5 ; extra == 'all'
Requires-Dist: jsonschema ; extra == 'all'
Requires-Dist: jupyter ; extra == 'all'
Requires-Dist: jupyter-client ; extra == 'all'
Requires-Dist: phx-class-registry ; extra == 'all'
Requires-Dist: requests ; extra == 'all'
Requires-Dist: streamlit ; extra == 'all'
Requires-Dist: tiktoken ; extra == 'all'
Requires-Dist: typing-extensions ; extra == 'all'
Requires-Dist: duckduckgo-search ==5.3.1b1 ; extra == 'all'
Provides-Extra: optional
Requires-Dist: google-search-results ; extra == 'optional'
Requires-Dist: lmdeploy >=0.2.3 ; extra == 'optional'
Requires-Dist: pillow ; extra == 'optional'
Requires-Dist: python-pptx ; extra == 'optional'
Requires-Dist: timeout-decorator ; extra == 'optional'
Requires-Dist: torch ; extra == 'optional'
Requires-Dist: transformers >=4.34 ; extra == 'optional'
Requires-Dist: vllm >=0.3.3 ; extra == 'optional'
